xain_aggregators/__init__.py
xain_aggregators/__version__.py
xain_aggregators/aggregator.py
xain_aggregators/model_sum.py
xain_aggregators/weighted_average.py
xain_aggregators-0.8.0.dist-info/METADATA
xain_aggregators-0.8.0.dist-info/WHEEL
xain_aggregators-0.8.0.dist-info/top_level.txt
xain_aggregators-0.8.0.dist-info/RECORD
